motivus/__init__.py
motivus/__main__.py
motivus/cli.py
motivus/client.py
motivus-2.4.0.dist-info/LICENSE
motivus-2.4.0.dist-info/METADATA
motivus-2.4.0.dist-info/WHEEL
motivus-2.4.0.dist-info/entry_points.txt
motivus-2.4.0.dist-info/top_level.txt
motivus-2.4.0.dist-info/RECORD
