Metadata-Version: 2.1
Name: motivus
Version: 2.4.0
Summary: Motivus client library
Home-page: https://motivus.cl
Author: Motivus SpA
Author-email: info@motivus.cl
License: GPLv3
Classifier: Programming Language :: Python :: 3
Classifier: Programming Language :: Python :: 3.7
Requires-Python: >=3.7
License-File: LICENSE
Requires-Dist: websockets (==8.1)
Requires-Dist: asyncio (==3.4.3)
Requires-Dist: pyyaml (==6.0)
Requires-Dist: requests (==2.26.0)
Requires-Dist: argparse (==1.4.0)
Requires-Dist: python-dotenv (==0.19.2)
